[
  {
    "id": "1",
    "title": "Prva Mojsijeva",
    "author": "Mojsije",
    "biblePart": "Zakoni",
    "slug": "prva-mojsijeva"
  },
  {
    "id": "2",
    "title": "Druga Mojsijeva",
    "author": "Mojsije",
    "biblePart": "Zakoni",
    "slug": "druga-mojsijeva"
  },
  {
    "id": "3",
    "title": "Isus Navin",
    "author": "Isus Navin",
    "biblePart": "Proroci",
    "slug": "isusa-navina"
  },
  {
    "id": "4",
    "title": "Isajija",
    "author": "Mojsije",
    "biblePart": "Proroci",
    "slug": "isajija"
  }
]
